README.md
setup.cfg
setup.py
anon/__init__.py
anon/basemodel.py
anon/client.py
anon/exceptions.py
anon/auth/__init__.py
anon/auth/tokens.py
anon/auth/users.py
anon/contrib/__init__.py
anon/contrib/utils.py
anon/contrib/downloaders/__init__.py
anon/contrib/exporters/__init__.py
anon/contrib/importers/__init__.py
anon/contrib/importers/utils.py
anon/contrib/infer/__init__.py
anon/infer/__init__.py
anon/infer/folders.py
anon/infer/presign.py
anon/infer/types.py
anon/infer/images/__init__.py
anon/infer/videos/__init__.py
anon/types/__init__.py
anon/types/bounding_box.py
anon/types/polygon.py
anon/utils/__init__.py
anon/utils/videos.py
anon_sdk.egg-info/PKG-INFO
anon_sdk.egg-info/SOURCES.txt
anon_sdk.egg-info/dependency_links.txt
anon_sdk.egg-info/requires.txt
anon_sdk.egg-info/top_level.txt
tests/__init__.py
tests/conftest.py