Metadata-Version: 2.1
Name: anon-sdk
Version: 0.0.1
Summary: python sdk to get data from anon
Home-page: https://github.com/streamingo/anon
Author: Streamingo Solutions
Author-email: deeplabel-team@streamingo.ai
License: UNKNOWN
Project-URL: Bug Reports, https://github.com/streamingo/anon/issues
Project-URL: Source, https://github.com/streamingo/anon/
Platform: UNKNOWN
Classifier: Development Status :: 3 - Alpha
Classifier: Intended Audience :: Developers
Classifier: Topic :: Software Development :: Build Tools
Classifier: License :: OSI Approved :: MIT License
Classifier: Programming Language :: Python :: 3
Classifier: Programming Language :: Python :: 3.6
Classifier: Programming Language :: Python :: 3.7
Classifier: Programming Language :: Python :: 3.8
Classifier: Programming Language :: Python :: 3.9
Classifier: Programming Language :: Python :: 3.10
Classifier: Programming Language :: Python :: 3 :: Only
Requires-Python: >=3.8, <4
